[{"search":"{tables}","replace":"transactions"},{"search":"/*fields*/","replace":"$table->string('slug',40)->unique();\n$table->integer('account_id')->nullable()->unsigned();\n$table->integer('sundry_id')->nullable()->unsigned();\n$table->integer('meter_id')->nullable()->unsigned();\n$table->integer('company_id')->nullable()->unsigned();\n$table->string('amount',10,2);\n$table->string('reference',45);\n$table->string('type',45);\n$table->string('description',250)->nullable();\n"},{"search":"/*foreign*/","replace":"$table->foreign('account_id')->references('id')->on('accounts')->onDelete('cascade');\n$table->foreign('sundry_id')->references('id')->on('sundries')->onDelete('cascade');\n$table->foreign('meter_id')->references('id')->on('meters')->onDelete('cascade');\n$table->foreign('company_id')->references('id')->on('companies')->onDelete('cascade');\n"}]